setup.py
bench/__init__.py
bench/cli.py
bench_cxy.egg-info/PKG-INFO
bench_cxy.egg-info/SOURCES.txt
bench_cxy.egg-info/dependency_links.txt
bench_cxy.egg-info/entry_points.txt
bench_cxy.egg-info/not-zip-safe
bench_cxy.egg-info/requires.txt
bench_cxy.egg-info/top_level.txt